qvalve-1.0.4.dist-info/METADATA
qvalve-1.0.4.dist-info/WHEEL
qvalve-1.0.4.dist-info/entry_points.txt
qvalve-1.0.4.dist-info/licenses/LICENSE
qvalve/__init__.py
qvalve/__main__.py
qvalve/cli.py
qvalve/data/gamebots.csv
qvalve/flaskapp/__init__.py
qvalve/flaskapp/forms.py
qvalve/flaskapp/routes.py
qvalve/flaskapp/static/app.js
qvalve/flaskapp/static/style.css
qvalve/flaskapp/templates/base.html
qvalve/flaskapp/templates/index.html
qvalve/gameserver.py
qvalve/mainserver.py
qvalve/reports.py
qvalve-1.0.4.dist-info/RECORD
