Metadata-Version: 2.1
Name: qvalve
Version: 1.0.4
Summary: Query Valve Main and Game Servers
Keywords: tf2,team-fortress-2,steam,valve
Author-Email: Russel Lane <russel@rlane.com>
License: MIT
Classifier: Development Status :: 4 - Beta
Classifier: Intended Audience :: End Users/Desktop
Classifier: License :: OSI Approved :: MIT License
Classifier: Programming Language :: Python :: 3
Classifier: Topic :: Games/Entertainment :: First Person Shooters
Project-URL: Homepage, https://github.com/russellane/qvalve
Requires-Python: >=3.10
Requires-Dist: bootstrap-flask>=2.4.1
Requires-Dist: flask-table>=0.5.0
Requires-Dist: flask-wtf>=1.2.2
Requires-Dist: flask>=3.1.0
Requires-Dist: loguru>=0.7.2
Requires-Dist: pandas>=2.2.3
Requires-Dist: rlane-libcli>=1.0.8
Requires-Dist: steam>=1.4.4
Requires-Dist: wtforms>=3.2.1
